RC23104UNO/__init__.py
RC23104UNO/metodos_lineales.py
RC23104UNO/metodos_no_lineales.py
RC23104UNO/utils.py
rc23104uno-0.1.3.dist-info/licenses/LICENSE
rc23104uno-0.1.3.dist-info/METADATA
rc23104uno-0.1.3.dist-info/WHEEL
rc23104uno-0.1.3.dist-info/top_level.txt
rc23104uno-0.1.3.dist-info/RECORD
