Metadata-Version: 2.4
Name: RC23104UNO
Version: 0.1.3
Summary: Librería para resolver sistemas de ecuaciones lineales y no lineales
Home-page: https://github.com/stan23rzc/RC23104UNO.git
Author: Stanley Ramirez
Author-email: stanleyramirez087@gmail.com
Classifier: Programming Language :: Python :: 3
Classifier: License :: OSI Approved :: MIT License
Classifier: Operating System :: OS Independent
Requires-Python: >=3.6
License-File: LICENSE
Requires-Dist: numpy>=1.19.0
Dynamic: author
Dynamic: author-email
Dynamic: classifier
Dynamic: description
Dynamic: description-content-type
Dynamic: home-page
Dynamic: license-file
Dynamic: requires-dist
Dynamic: requires-python
Dynamic: summary
